elasticnet/__init__.py
elasticnet/__main__.py
elasticnet/ann.py
elasticnet/lib.py
elasticnet/main.py
elasticnet/prepare_input.py
elasticnet-1.0.4.dist-info/LICENSE
elasticnet-1.0.4.dist-info/METADATA
elasticnet-1.0.4.dist-info/WHEEL
elasticnet-1.0.4.dist-info/top_level.txt
elasticnet-1.0.4.dist-info/RECORD
