Metadata-Version: 2.1
Name: elasticnet
Version: 1.0.4
Summary: Predict the mechanical properties of multi-component transition metal carbides (MTMCs).
Home-page: https://github.com/jzhang-github/MTMC_elastic_modulus
Author: ZHANG Jun; ZHAO Shijun
Author-email: j.zhang@my.cityu.edu.hk
License: MIT
Platform: all
Classifier: Development Status :: 3 - Alpha
Classifier: License :: OSI Approved :: MIT License
Classifier: Intended Audience :: Developers
Classifier: Operating System :: OS Independent
Classifier: Natural Language :: English
Classifier: Programming Language :: Python
Classifier: Programming Language :: Python :: 3.10
Classifier: Topic :: Software Development :: Libraries
Requires-Python: >=3.9
License-File: LICENSE
Requires-Dist: numpy >=1.25.0
Requires-Dist: scikit-learn ==1.2.2
Requires-Dist: tensorflow ==2.10.0
Requires-Dist: ase ==3.22.1
Requires-Dist: pandas ==1.5.3
Requires-Dist: openpyxl ==3.0
